fmu/__init__.py
fmu/pem/__init__.py
fmu/pem/__main__.py
fmu/pem/run_pem.py
fmu/pem/version.py
fmu/pem/forward_models/__init__.py
fmu/pem/forward_models/pem_model.py
fmu/pem/hook_implementations/__init__.py
fmu/pem/hook_implementations/jobs.py
fmu/pem/pem_functions/__init__.py
fmu/pem/pem_functions/density.py
fmu/pem/pem_functions/effective_pressure.py
fmu/pem/pem_functions/estimate_saturated_rock.py
fmu/pem/pem_functions/fluid_properties.py
fmu/pem/pem_functions/mineral_properties.py
fmu/pem/pem_functions/pressure_sensitivity.py
fmu/pem/pem_functions/regression_models.py
fmu/pem/pem_functions/run_friable_model.py
fmu/pem/pem_functions/run_patchy_cement_model.py
fmu/pem/pem_functions/run_t_matrix_model.py
fmu/pem/pem_utilities/__init__.py
fmu/pem/pem_utilities/cumsum_properties.py
fmu/pem/pem_utilities/delta_cumsum_time.py
fmu/pem/pem_utilities/enum_defs.py
fmu/pem/pem_utilities/export_routines.py
fmu/pem/pem_utilities/fipnum_pvtnum_utilities.py
fmu/pem/pem_utilities/import_config.py
fmu/pem/pem_utilities/import_routines.py
fmu/pem/pem_utilities/pem_class_definitions.py
fmu/pem/pem_utilities/pem_config_validation.py
fmu/pem/pem_utilities/rpm_models.py
fmu/pem/pem_utilities/update_grid.py
fmu/pem/pem_utilities/utils.py
fmu_pem-0.0.3.dist-info/licenses/LICENSE
fmu_pem-0.0.3.dist-info/METADATA
fmu_pem-0.0.3.dist-info/WHEEL
fmu_pem-0.0.3.dist-info/entry_points.txt
fmu_pem-0.0.3.dist-info/top_level.txt
fmu_pem-0.0.3.dist-info/RECORD
