Metadata-Version: 2.4
Name: fmu-pem
Version: 0.0.3
Summary: pem
License:                     GNU GENERAL PUBLIC LICENSE
Project-URL: Homepage, https://github.com/equinor/fmu-pem
Project-URL: Repository, https://github.com/equinor/fmu-pem
Keywords: energy,subsurface,seismic,scientific,engineering
Classifier: Intended Audience :: Science/Research
Classifier: Topic :: Scientific/Engineering
Classifier: Topic :: Scientific/Engineering :: Physics
Classifier: Topic :: Software Development :: Libraries
Classifier: Topic :: Utilities
Classifier: Operating System :: POSIX :: Linux
Classifier: Natural Language :: English
Requires-Python: >=3.11
License-File: LICENSE
Requires-Dist: numpy>=1.24.3
Requires-Dist: xtgeo>=4.7.1
Requires-Dist: fmu-tools
Requires-Dist: fmu-config
Requires-Dist: fmu-dataio
Requires-Dist: rock-physics-open>=0.3.3
Requires-Dist: PyYAML>=6.0.1
Requires-Dist: pydantic
Requires-Dist: ert>=14.1.10
Provides-Extra: tests
Requires-Dist: mypy; extra == "tests"
Requires-Dist: pytest; extra == "tests"
Requires-Dist: pytest-cov; extra == "tests"
Requires-Dist: pytest-xdist; extra == "tests"
Requires-Dist: ruff; extra == "tests"
Provides-Extra: docs
Requires-Dist: autoapi; extra == "docs"
Requires-Dist: sphinx; extra == "docs"
Requires-Dist: sphinx-argparse; extra == "docs"
Requires-Dist: sphinx-autodoc-typehints; extra == "docs"
Requires-Dist: sphinx-copybutton; extra == "docs"
Requires-Dist: sphinx-togglebutton; extra == "docs"
Requires-Dist: sphinx_rtd_theme; extra == "docs"
Dynamic: license-file
